cyto_studio/__init__.py
cyto_studio/__main__.py
cyto_studio/custom.qss
cyto_studio/custom_qt_dims_slider.py
cyto_studio/cyto_studio.py
cyto_studio/data.py
cyto_studio/icon.png
cyto_studio/logo.png
cyto_studio/my_widgets.py
cyto_studio/utilities.py
cyto_studio-0.2.20.dist-info/LICENSE
cyto_studio-0.2.20.dist-info/METADATA
cyto_studio-0.2.20.dist-info/WHEEL
cyto_studio-0.2.20.dist-info/entry_points.txt
cyto_studio-0.2.20.dist-info/top_level.txt
cyto_studio-0.2.20.dist-info/RECORD
