Metadata-Version: 2.1
Name: cyto-studio
Version: 0.2.20
Summary: napari viewer which can read multiplex images as zarr files
Home-page: https://github.com/TristanWhitmarsh/cyto-studio
Author: Tristan Whitmarsh
Author-email: tw401@cam.ac.uk
License: GNU
Platform: UNKNOWN
Classifier: License :: OSI Approved :: GNU Affero General Public License v3
Classifier: Programming Language :: Python :: 3
License-File: LICENSE
Requires-Dist: napari[pyside2] (==0.5.6)
Requires-Dist: PySide2 (==5.15.2.1)
Requires-Dist: xarray (==2023.4.2)
Requires-Dist: zarr (==2.14.2)
Requires-Dist: SimpleITK (==2.2.1)
Requires-Dist: napari-animation (==0.0.8)
Requires-Dist: tifffile (==2023.4.12)
Requires-Dist: pyarrow (==19.0.1)
Requires-Dist: opencv-python-headless (>=4.5.1.48)
Requires-Dist: numpy (==1.23.5)
Requires-Dist: pydantic (==1.10.15)
Requires-Dist: geopandas (==1.0.1)
